cython_bbox.cpython-39-darwin.so
cython_bbox_fix-2023.4.21.dist-info/LICENSE
cython_bbox_fix-2023.4.21.dist-info/METADATA
cython_bbox_fix-2023.4.21.dist-info/WHEEL
cython_bbox_fix-2023.4.21.dist-info/top_level.txt
cython_bbox_fix-2023.4.21.dist-info/RECORD
