Metadata-Version: 2.1
Name: cython-bbox-fix
Version: 2023.4.21
Summary: Standalone cython_bbox
Home-page: https://github.com/samson-wang/cython_bbox.git
Keywords: cython_bbox_fix
License-File: LICENSE
Requires-Dist: Cython
Requires-Dist: numpy
